thoth/sourcemanagement/__init__.py
thoth/sourcemanagement/enums.py
thoth/sourcemanagement/exception.py
thoth/sourcemanagement/github_authentication.py
thoth/sourcemanagement/sourcemanagement.py
thoth_sourcemanagement-0.4.3.dist-info/LICENSE
thoth_sourcemanagement-0.4.3.dist-info/METADATA
thoth_sourcemanagement-0.4.3.dist-info/WHEEL
thoth_sourcemanagement-0.4.3.dist-info/top_level.txt
thoth_sourcemanagement-0.4.3.dist-info/RECORD
