Metadata-Version: 2.1
Name: thoth-sourcemanagement
Version: 0.4.3
Summary: This package helps thoth app's interact with git forges like Github, Gitlab.
Home-page: https://github.com/thoth-station/source-management
Author: Sai Sankar Gochhayat
Author-email: saisankargochhayat@gmail.com
License: GPLv3+
Classifier: Programming Language :: Python :: 3
Classifier: License :: OSI Approved :: GNU General Public License v3 or later (GPLv3+)
Classifier: Operating System :: OS Independent
Requires-Python: >=3.6
License-File: LICENSE
Requires-Dist: ogr
Requires-Dist: requests
Requires-Dist: delegator.py
